{
  "mcq": [
    {
      "statement": "How does derivative spectroscopy aid in the determination of the mechanism of a chemical reaction?",
      "options": {
        "a": "By quantifying changes in activation energy",
        "b": "By providing information on reaction intermediates",
        "c": "By directly mentioning the rate constants values for the reaction",
        "d": "By measuring changes in the enthalpy of reaction"
      },
      "correct_option": "b",
      "one_liner": "",
      "suggestions": []
    }
  ]
}