{
  "mcq": [
    {
      "statement": "In which years did Shah Wali-Ullah translate the Quran into Persian?",
      "options": {
        "a": "1720-21",
        "b": "1737-38",
        "c": "1750-51",
        "d": "None of these"
      },
      "one_liner": "Shah Wali-Ullah translated the Quran into Persian during the years **1737-38**.",
      "correct_option": "b",
      "suggestions": [
        {
          "topic": "Decline: Ahmad Sirhindi, Shah Waliullah, Maratha Empire 1674-1818",
          "chapter": "Mughal Era and Decline"
        },
        {
          "topic": "Mughals 1526 - 1857",
          "chapter": "Mughal Era and Decline"
        },
        {
          "topic": "Muhi-ud-Din Muhammad/ Aurangzeb Alamgir 1658 - 1707",
          "chapter": "Mughal Era and Decline"
        },
        {
          "topic": "Decline: Ahmad Sirhindi, Shah Waliullah, Maratha Empire 1674-1818",
          "chapter": "Mughal Era and Decline"
        }
      ]
    }
  ],
  "is_new": true
}