{
  "mcq": [
    {
      "statement": "Who led the Pirpur Report of 1938 that highlighted the exploitation of Muslims under Congress ministries?",
      "options": {
        "a": "M. S. Sharif",
        "b": "Kamal Yar Jung",
        "c": "Raja Syed Muhammad Mehndi of Peerpur",
        "d": "Maulana Azad"
      },
      "one_liner": "The Pirpur Report of 1938, which exposed the exploitation of Muslims under Congress ministries, was led by **Raja Syed Muhammad Mehndi of Peerpur**.",
      "correct_option": "c",
      "suggestions": [
        {
          "topic": "Resignation of Congress Ministries",
          "chapter": "Constitutional & Political Developments"
        },
        {
          "topic": "Day of Deliverance",
          "chapter": "Constitutional & Political Developments"
        },
        {
          "topic": "Govt. of India Act 1935",
          "chapter": "Constitutional & Political Developments"
        },
        {
          "topic": "Resignation of Congress Ministries",
          "chapter": "Constitutional & Political Developments"
        }
      ]
    }
  ],
  "is_new": true
}