{
  "mcq": [
    {
      "statement": "For how many years did the Sayyid Dynasty rule after its establishment in 1414?",
      "options": {
        "a": "20 years",
        "b": "50 years",
        "c": "37 years",
        "d": "10 years"
      },
      "one_liner": "The Sayyid Dynasty ruled for **37 years** after its establishment in 1414.",
      "correct_option": "c",
      "suggestions": [
        {
          "topic": "Sayyid Dynasty (1414-1451)",
          "chapter": "Early Islamic and Medieval Period"
        },
        {
          "topic": "Delhi Sultanate (1206-1526)",
          "chapter": "Early Islamic and Medieval Period"
        },
        {
          "topic": "Lodhi Dynasty (1451-1526)",
          "chapter": "Early Islamic and Medieval Period"
        },
        {
          "topic": "Sayyid Dynasty (1414-1451)",
          "chapter": "Early Islamic and Medieval Period"
        }
      ]
    }
  ],
  "is_new": true
}