{
  "mcq": [
    {
      "statement": "Which Roman goddess is depicted by the Statue of Liberty?",
      "options": {
        "a": "Venus",
        "b": "Minerva",
        "c": "Libertas",
        "d": "Juno"
      },
      "one_liner": "The Statue of Liberty represents **Libertas**, the Roman goddess of liberty.",
      "correct_option": "c",
      "suggestions": [
        {
          "topic": "Statue of Liberty",
          "chapter": "World Historic Landmarks & Buildings"
        },
        {
          "topic": "Worldwide Famous Historic Buildings",
          "chapter": "World Historic Landmarks & Buildings"
        },
        {
          "topic": "United States of America",
          "chapter": "Countries of the World"
        },
        {
          "topic": "Statue of Liberty",
          "chapter": "World Historic Landmarks & Buildings"
        }
      ]
    }
  ],
  "is_new": true
}