{
  "mcq": [
    {
      "statement": "In which year did Jabir Bin Hayan die?",
      "options": {
        "a": "815 AD",
        "b": "820 AD",
        "c": "800 AD",
        "d": "830 AD"
      },
      "one_liner": "Jabir Bin Hayan passed away in the year **815 AD**.",
      "correct_option": "a",
      "suggestions": [
        {
          "topic": "Prominent Muslim Scientists",
          "chapter": "Prominent Scientists"
        },
        {
          "topic": "Prominent Scientists of the World",
          "chapter": "Prominent Scientists"
        },
        {
          "topic": "Pakistani Scientists",
          "chapter": "Prominent Scientists"
        },
        {
          "topic": "Prominent Muslim Scientists",
          "chapter": "Prominent Scientists"
        }
      ]
    }
  ],
  "is_new": true,
  "year": 2001
}