{
  "mcq": [
    {
      "statement": "Which of the following statements is true about hydrogen gas?",
      "options": {
        "a": "It is combustible",
        "b": "It is non-combustible",
        "c": "It is inert",
        "d": "None of these"
      },
      "one_liner": "Hydrogen gas is known for being **combustible**, meaning it can catch fire and burn easily.",
      "correct_option": "a",
      "suggestions": [
        {
          "topic": "Some Important Elements",
          "chapter": "Chemistry in Everyday Life"
        },
        {
          "topic": "Element",
          "chapter": "Chemistry in Everyday Life"
        },
        {
          "topic": "Chemistry",
          "chapter": "Chemistry in Everyday Life"
        },
        {
          "topic": "Some Important Elements",
          "chapter": "Chemistry in Everyday Life"
        }
      ]
    }
  ],
  "is_new": true,
  "year": 2001
}