{
  "mcq": [
    {
      "statement": "Which is the largest cantonment of Pakistan?",
      "options": {
        "a": "Rawalpindi",
        "b": "Lahore",
        "c": "Kharian",
        "d": "Quetta"
      },
      "one_liner": "Kharian is recognized as the **largest cantonment of Pakistan**.",
      "correct_option": "c",
      "suggestions": [
        {
          "topic": "Geographical Tags Attached with Names of Different Countries and Cities",
          "chapter": "Geography, Boundaries & Places"
        },
        {
          "topic": "Changed Names of Different Countries and Cities",
          "chapter": "Geography, Boundaries & Places"
        },
        {
          "topic": "Miscellaneous Facts of GK",
          "chapter": "Miscellaneous"
        },
        {
          "topic": "Geographical Tags Attached with Names of Different Countries and Cities",
          "chapter": "Geography, Boundaries & Places"
        }
      ]
    }
  ],
  "is_new": true
}