{
  "mcq": [
    {
      "statement": "What are the temporary lakes found in the sandy areas of the Balochistan Plateau called?",
      "options": {
        "a": "Hamuns",
        "b": "Dhoros",
        "c": "Tarns",
        "d": "None of these"
      },
      "one_liner": "The temporary lakes in the Balochistan Plateau that only contain water during the rainy season are known as **Hamuns**.",
      "correct_option": "a",
      "suggestions": [
        {
          "topic": "Plateaus in Pakistan",
          "chapter": "Physical Geography of Pakistan"
        },
        {
          "topic": "Gas Companies and Refineries",
          "chapter": "Natural Resources & Energy"
        },
        {
          "topic": "Geography of Pakistan",
          "chapter": "Physical Geography of Pakistan"
        },
        {
          "topic": "Plateaus in Pakistan",
          "chapter": "Physical Geography of Pakistan"
        }
      ]
    }
  ],
  "is_new": true
}