{
  "mcq": [
    {
      "statement": "How many major oceans are labeled on the described world map?",
      "options": {
        "a": "Three",
        "b": "Four",
        "c": "Five",
        "d": "None of these"
      },
      "one_liner": "There are **four** major oceans labeled on the described world map: Arctic, Pacific, Atlantic, and Indian.",
      "correct_option": "b",
      "suggestions": [
        {
          "topic": "Famous Oceans of the World",
          "chapter": "Physical Geography of the World"
        },
        {
          "topic": "Geography of World",
          "chapter": "Continents & World Regions"
        },
        {
          "topic": "Geographical Terms",
          "chapter": "Physical Geography of the World"
        },
        {
          "topic": "Famous Oceans of the World",
          "chapter": "Physical Geography of the World"
        }
      ]
    }
  ],
  "is_new": true
}