{
  "mcq": [
    {
      "statement": "Why did the All-India Muslim League reject the Cripps Mission proposals?",
      "options": {
        "a": "Lack of autonomy",
        "b": "No separate state for Muslims",
        "c": "Opposition to British rule",
        "d": "None of these"
      },
      "one_liner": "The All-India Muslim League rejected the Cripps Mission proposals because **there was no plan for making a separate state for Muslims**.",
      "correct_option": "b",
      "suggestions": [
        {
          "topic": "Cripps Mission",
          "chapter": "Road to Independence"
        },
        {
          "topic": "Interim Government",
          "chapter": "Road to Independence"
        },
        {
          "topic": "Govt. of India Act 1919",
          "chapter": "Constitutional & Political Developments"
        },
        {
          "topic": "Cripps Mission",
          "chapter": "Road to Independence"
        }
      ]
    }
  ],
  "is_new": true
}