{
  "mcq": [
    {
      "statement": "According to the 14 Points, which provinces should have reforms introduced on the same pattern as other provinces?",
      "options": {
        "a": "Sind and Balochistan",
        "b": "NWFP and Baluchistan",
        "c": "Punjab and Bengal",
        "d": "None of these"
      },
      "one_liner": "The 14 Points called for reforms in **North-West Frontier Province and Baluchistan** on the same pattern as in other provinces.",
      "correct_option": "b",
      "suggestions": [
        {
          "topic": "Fourteen Points of Quaid-e-Azam",
          "chapter": "Constitutional & Political Developments"
        },
        {
          "topic": "Nehru Report",
          "chapter": "Constitutional & Political Developments"
        },
        {
          "topic": "Muslim League (1906)",
          "chapter": "Political Organizations & Muslim Struggle"
        },
        {
          "topic": "Fourteen Points of Quaid-e-Azam",
          "chapter": "Constitutional & Political Developments"
        }
      ]
    }
  ],
  "is_new": true
}