{
  "mcq": [
    {
      "statement": "Which Act enlarged the size of both the Central and Provincial Legislative Councils in India?",
      "options": {
        "a": "Act of 1858",
        "b": "Act of 1909",
        "c": "Act of 1919",
        "d": "None of these"
      },
      "one_liner": "The size of both the Central and Provincial Legislative Councils in India was enlarged by the **Act of 1909**.",
      "correct_option": "b",
      "suggestions": [
        {
          "topic": "Minto-Morley Reforms (1909)",
          "chapter": "Political Organizations & Muslim Struggle"
        },
        {
          "topic": "Indian Councils Act (1892)",
          "chapter": "Political Organizations & Muslim Struggle"
        },
        {
          "topic": "Govt. of India Act 1919",
          "chapter": "Constitutional & Political Developments"
        },
        {
          "topic": "Minto-Morley Reforms (1909)",
          "chapter": "Political Organizations & Muslim Struggle"
        }
      ]
    }
  ],
  "is_new": true,
  "year": 2001
}