{
  "mcq": [
    {
      "statement": "Where was Muhammad bin Qasim when he was commissioned to lead the expedition to Sind?",
      "options": {
        "a": "Basra",
        "b": "Faras (Iran)",
        "c": "Baghdad",
        "d": "Debal"
      },
      "one_liner": "Muhammad bin Qasim was at **Faras (Iran)** when he was commissioned to lead the expedition to Sind.",
      "correct_option": "b",
      "suggestions": [
        {
          "topic": "Arrival of Muhammad bin Qasim to Subcontinent (712)",
          "chapter": "Early Islamic and Medieval Period"
        },
        {
          "topic": "Early Islamic Rule in Sub-continent",
          "chapter": "Early Islamic and Medieval Period"
        },
        {
          "topic": "Miscellaneous",
          "chapter": "Ancient Empires"
        },
        {
          "topic": "Arrival of Muhammad bin Qasim to Subcontinent (712)",
          "chapter": "Early Islamic and Medieval Period"
        }
      ]
    }
  ],
  "is_new": true
}