{
  "mcq": [
    {
      "statement": "What majority is required to amend the 1973 Constitution of Pakistan?",
      "options": {
        "a": "Simple majority",
        "b": "Two-thirds majority",
        "c": "Three-fourths majority",
        "d": "None of these"
      },
      "one_liner": "A two-thirds majority of the Parliament is required to amend the **1973 Constitution of Pakistan**.",
      "correct_option": "b",
      "suggestions": [
        {
          "topic": "Constitution",
          "chapter": "Constitution & Amendments"
        },
        {
          "topic": "Important Events (1971-1980)",
          "chapter": "Early State Formation and Events"
        },
        {
          "topic": "List of All Prime Ministers",
          "chapter": "Political Structure and Leadership"
        },
        {
          "topic": "Initial Constitution Making Hurdles",
          "chapter": "Constitution & Amendments"
        }
      ]
    }
  ],
  "is_new": true
}