{
  "mcq": [
    {
      "statement": "Which city was the host for the 2024 Summer Olympics?",
      "options": {
        "a": "London",
        "b": "Paris",
        "c": "Los Angeles",
        "d": "Tokyo"
      },
      "one_liner": "The city of **Paris** served as the host for the 2024 Summer Olympics.",
      "correct_option": "b",
      "suggestions": [
        {
          "topic": "Summer Olympics",
          "chapter": "Culture, Sports & Pakistani Honors"
        },
        {
          "topic": "Olympics",
          "chapter": "Culture, Sports & Pakistani Honors"
        },
        {
          "topic": "Sports at a Glance",
          "chapter": "Culture, Sports & Pakistani Honors"
        },
        {
          "topic": "2024 Summer Olympics",
          "chapter": "Culture, Sports & Pakistani Honors"
        }
      ]
    }
  ],
  "is_new": true
}