{
  "mcq": [
    {
      "statement": "Major Raja Aziz Bhatti, known as Muhafiz-e-Lahore, was martyred in which war?",
      "options": {
        "a": "Indo-Pakistani War of 1947",
        "b": "Indo-Pakistani War of 1965",
        "c": "Indo-Pakistani War of 1971",
        "d": "Kargil War"
      },
      "one_liner": "Major Raja Aziz Bhatti, also known as Muhafiz-e-Lahore, was martyred in the **Indo-Pakistani War of 1965**.",
      "correct_option": "b",
      "suggestions": [
        {
          "topic": "Nishan-e-Haider",
          "chapter": "Culture, Sports & Pakistani Honors"
        },
        {
          "topic": "Important Events (1948)",
          "chapter": "Early State Formation and Events"
        },
        {
          "topic": "Important Events (1971-1980)",
          "chapter": "Early State Formation and Events"
        },
        {
          "topic": "Nishan-e-Haider",
          "chapter": "Culture, Sports & Pakistani Honors"
        }
      ]
    }
  ],
  "is_new": true
}