{
  "mcq": [
    {
      "statement": "\"کپاس کا پھول\" کس مصنف کے افسانوی مجموعہ کا نام ہے؟",
      "options": {
        "a": "احمد ندیم قاسمی",
        "b": "منٹو",
        "c": "بانو قدسیہ",
        "d": "اشفاق احمد"
      },
      "one_liner": "\"کپاس کا پھول\" احمد ندیم قاسمی کے افسانوں کے مجموعہ کا نام ہے اور اس کے مصنف **احمد ندیم قاسمی** ہیں۔",
      "correct_option": "a",
      "suggestions": [
        {
          "topic": "Ahmad Nadeem Qasmi",
          "chapter": "اردو ادب کی اہم شخصیات اور انکی تصانیف"
        }
      ]
    }
  ],
  "is_new": true
}