{
  "mcq": [
    {
      "statement": "ترکیب بند کیا ہے؟",
      "options": {
        "a": "وہ نظم جو ایک بند پر مشتمل ہو",
        "b": "وہ نظم جو متعدد بندوں پر مشتمل ہو",
        "c": "وہ نظم جو صرف غزل ہو",
        "d": "ان میں سے کوئی نہیں"
      },
      "one_liner": "ترکیب بند وہ نظم ہے جو متعدد بندوں پر مشتمل ہو، اس لیے ترکیب بند نظم کی بنیادی خصوصیت اس کا کئی بندوں پر مشتمل ہونا ہے۔",
      "correct_option": "b",
      "suggestions": [
        {
          "topic": "ترکیب بند اور ترجیع بند",
          "chapter": "اردوشاعری کی اصناف"
        }
      ]
    }
  ],
  "is_new": true
}