{
  "mcq": [
    {
      "statement": "'ضرب کلیم' میں علامہ اقبال نے جدید تہذیب کے مسائل کی بنیادی وجہ کیا بیان کی ہے؟",
      "options": {
        "a": "مادیت",
        "b": "ناانصافی",
        "c": "لادینیت",
        "d": "مندرجہ بالا تمام"
      },
      "one_liner": "علامہ اقبال نے 'ضرب کلیم' میں جدید تہذیب کے مسائل کی بنیادی وجہ **مادیت، ناانصافی اور لادینیت** کو قرار دیا ہے۔",
      "correct_option": "d",
      "suggestions": [
        {
          "topic": "Allam Muhammad Iqbal",
          "chapter": "اردو ادب کی اہم شخصیات اور انکی تصانیف"
        }
      ]
    }
  ],
  "is_new": true
}