{
  "mcq": [
    {
      "statement": "اسم علم کی وہ قسم جس میں والد یا والدہ کے نام کی نسبت ہو، کیا کہلاتی ہے؟",
      "options": {
        "a": "کنیت",
        "b": "عرف",
        "c": "لقب",
        "d": "تخلص"
      },
      "one_liner": "اسم علم کی وہ قسم جس میں والد یا والدہ کے نام کی نسبت ہو، اسے **کنیت** کہتے ہیں۔",
      "correct_option": "a",
      "suggestions": [
        {
          "topic": "اسم  علم کی قسمیں",
          "chapter": "اردو گرامر"
        }
      ]
    }
  ],
  "is_new": true
}