{
  "mcq": [
    {
      "statement": "حضرت موہانی کا اصل نام کیا تھا؟",
      "options": {
        "a": "محی الدین احمد",
        "b": "فضل الحسن",
        "c": "شمس الدین محمد ولی",
        "d": "اسد اللہ خان"
      },
      "one_liner": "حضرت موہانی کا اصل نام **فضل الحسن** تھا، جو اردو ادب میں نمایاں مقام رکھتے ہیں۔",
      "correct_option": "b",
      "suggestions": [
        {
          "topic": "شاعروں اور ادیبوں کے قلمی اور اصلی نام",
          "chapter": "اردوشاعری کی اصناف"
        }
      ]
    }
  ],
  "is_new": true
}