{
  "mcq": [
    {
      "statement": "محاورہ 'آج مرے کل دوسرا دن' سے کیا مراد ہے؟",
      "options": {
        "a": "زندگی کی خوشی",
        "b": "زندگی کی بے ثباتی ظاہر ہوتی ہے",
        "c": "زندگی کی لمبائی",
        "d": "ان میں سے کوئی نہیں"
      },
      "one_liner": "محاورہ 'آج مرے کل دوسرا دن' **زندگی کی بے ثباتی** کو ظاہر کرتا ہے۔",
      "correct_option": "b",
      "suggestions": [
        {
          "topic": "محارہ",
          "chapter": "زبان و بیان اور درستی"
        }
      ]
    }
  ],
  "is_new": true
}