{
  "mcq": [
    {
      "statement": "کتاب 'رحیق المختوم' کے مصنف کون ہیں؟",
      "options": {
        "a": "صفی الرحمان",
        "b": "اشفاق احمد",
        "c": "ابوالکلام آزاد",
        "d": "ان میں سے کوئی نہیں"
      },
      "one_liner": "کتاب 'رحیق المختوم' کے مصنف **صفی الرحمان** ہیں۔",
      "correct_option": "a",
      "suggestions": [
        {
          "topic": "Others",
          "chapter": "اردو ادب کی اہم شخصیات اور انکی تصانیف"
        }
      ]
    }
  ],
  "is_new": true,
  "year": 2001
}