{
  "mcq": [
    {
      "statement": "What does the idiom 'be on the point of something' mean?",
      "options": {
        "a": "To be located at a specific place",
        "b": "To be about to do something",
        "c": "To be confused about a decision",
        "d": "To be the most important part of something"
      },
      "one_liner": "The idiom 'be on the point of something' means to be on the verge of doing something or to be about to do something imminently.",
      "correct_option": "b",
      "suggestions": [
        {
          "topic": "Idioms",
          "chapter": "Vocabulary and Usage"
        }
      ]
    }
  ],
  "is_new": true
}