{
  "mcq": [
    {
      "statement": "Select the correct pair of synonym:antonym for the word 'vanity':",
      "options": {
        "a": "narcissism:modesty",
        "b": "egotism:arrogance",
        "c": "conceit:pride",
        "d": "self-love:selflessness"
      },
      "one_liner": "'Narcissism' is a synonym for 'vanity', while 'modesty' is its antonym.",
      "correct_option": "a",
      "suggestions": [
        {
          "topic": "Combined Vocabulary",
          "chapter": "Combined Vocabulary"
        }
      ]
    }
  ],
  "is_new": true
}