{
  "mcq": [
    {
      "statement": "Select the antonym of the word 'vituperative':",
      "options": {
        "a": "complimentary",
        "b": "abusive",
        "c": "derogatory",
        "d": "slanderous"
      },
      "one_liner": "The opposite of 'vituperative', which means harshly abusive, would be 'complimentary' or 'praiseful'.",
      "correct_option": "a",
      "suggestions": [
        {
          "topic": "Antonyms",
          "chapter": "Antonyms"
        }
      ]
    }
  ],
  "is_new": true
}