{
  "mcq": [
    {
      "statement": "Select the antonym of the word 'insensible':",
      "options": {
        "a": "unconscious",
        "b": "aware",
        "c": "unfeeling",
        "d": "indifferent"
      },
      "one_liner": "The word 'insensible' has antonyms like 'aware' and 'conscious', which denote the ability to perceive or feel.",
      "correct_option": "b",
      "suggestions": [
        {
          "topic": "Antonyms",
          "chapter": "Antonyms"
        }
      ]
    }
  ],
  "is_new": true
}