{
  "mcq": [
    {
      "statement": "If you want to pass your exams, you need to _______ and study hard.",
      "options": {
        "a": "run out",
        "b": "buckle down",
        "c": "break up",
        "d": "call off"
      },
      "one_liner": "If you want to pass your exams, you need to 'buckle down' and study hard.",
      "correct_option": "b",
      "suggestions": [
        {
          "topic": "Phrasal Verbs",
          "chapter": "Vocabulary and Usage"
        }
      ]
    }
  ],
  "is_new": true
}