{
  "mcq": [
    {
      "statement": "Select the synonym of the word 'sobriety':",
      "options": {
        "a": "intoxication",
        "b": "temperance",
        "c": "drunkenness",
        "d": "excess"
      },
      "one_liner": "'Sobriety' refers to the state of being sober or not intoxicated, similar to 'abstinence' or 'temperance'.",
      "correct_option": "b",
      "suggestions": [
        {
          "topic": "Synonyms",
          "chapter": "Synonyms"
        }
      ]
    }
  ],
  "is_new": true,
  "year": 2001
}