{
  "mcq": [
    {
      "statement": "Select the synonym of the phrase 'at sixes and sevens':",
      "options": {
        "a": "organized",
        "b": "disorder",
        "c": "harmony",
        "d": "peace"
      },
      "one_liner": "Being 'at sixes and sevens' is synonymous with being in a state of 'disorder' or 'confusion'.",
      "correct_option": "b",
      "suggestions": [
        {
          "topic": "Synonyms",
          "chapter": "Synonyms"
        }
      ]
    }
  ],
  "is_new": true,
  "year": 2001
}