{
  "mcq": [
    {
      "statement": "Select the antonym of the word 'disabuse':",
      "options": {
        "a": "enlighten",
        "b": "correct",
        "c": "mislead",
        "d": "inform"
      },
      "one_liner": "Antonyms of 'disabuse' include 'deceive' and 'mislead', both implying causing someone to believe something that is not true.",
      "correct_option": "c",
      "suggestions": [
        {
          "topic": "Antonyms",
          "chapter": "Antonyms"
        }
      ]
    }
  ],
  "is_new": true
}