{
  "mcq": [
    {
      "statement": "Select the antonym of the word 'conspire':",
      "options": {
        "a": "collaborate",
        "b": "plot",
        "c": "act independently",
        "d": "scheme"
      },
      "one_liner": "The opposite of 'conspire', which involves secret collaboration, would be to 'act independently' or 'work alone'.",
      "correct_option": "c",
      "suggestions": [
        {
          "topic": "Antonyms",
          "chapter": "Antonyms"
        }
      ]
    }
  ],
  "is_new": true
}