{
  "mcq": [
    {
      "statement": "Select the correct pair of synonym:antonym for the word 'lassitude':",
      "options": {
        "a": "lethargy:vigor",
        "b": "ennui:vivacity",
        "c": "fatigue:activity",
        "d": "weariness:strength"
      },
      "one_liner": "'Ennui' is a synonym of 'lassitude', reflecting a feeling of listlessness, while 'vivacity' is its antonym, indicating spirited energy.",
      "correct_option": "b",
      "suggestions": [
        {
          "topic": "Combined Vocabulary",
          "chapter": "Combined Vocabulary"
        }
      ]
    }
  ],
  "is_new": true
}