{
  "mcq": [
    {
      "statement": "Select the synonym of the word 'invincible':",
      "options": {
        "a": "vulnerable",
        "b": "unconquerable",
        "c": "weak",
        "d": "defeated"
      },
      "one_liner": "'Invincible' means incapable of being defeated, making 'unconquerable' a fitting synonym.",
      "correct_option": "b",
      "suggestions": [
        {
          "topic": "Synonyms",
          "chapter": "Synonyms"
        }
      ]
    }
  ],
  "is_new": true,
  "year": 2001
}