{
  "mcq": [
    {
      "statement": "Select the correct pair of synonym:antonym for the word 'carnivore':",
      "options": {
        "a": "meat-eater:plant-eater",
        "b": "predator:omnivore",
        "c": "hunter:herbivore",
        "d": "scavenger:vegetarian"
      },
      "one_liner": "'Meat-eater' is a synonym of 'carnivore', while 'plant-eater' is its antonym.",
      "correct_option": "a",
      "suggestions": [
        {
          "topic": "Combined Vocabulary",
          "chapter": "Combined Vocabulary"
        }
      ]
    }
  ],
  "is_new": true
}