{
  "mcq": [
    {
      "statement": "Choose the sentence with correct order of adjectives: I met, young two, beautiful, British girls at the airport",
      "options": {
        "a": "I met, young two, beautiful, British girls at the airport.",
        "b": "I met two beautiful, young, British girls at the airport.",
        "c": "I met two, British, young, beautiful girls at the airport.",
        "d": "I met two young, beautiful British girls, at the airport."
      },
      "correct_option": "d",
      "one_liner": "",
      "suggestions": []
    }
  ]
}