{
  "mcq": [
    {
      "statement": "What does the word 'REX' stand for?",
      "options": {
        "a": "Queen",
        "b": "King",
        "c": "Prince",
        "d": "Duke"
      },
      "one_liner": "The word 'REX' is used to denote the **King**.",
      "correct_option": "b",
      "suggestions": [
        {
          "topic": "United Kingdom",
          "chapter": "Countries of the World"
        },
        {
          "topic": "Some Famous Prime Ministers of United Kingdom",
          "chapter": "Countries of the World"
        },
        {
          "topic": "Miscellaneous Facts of GK",
          "chapter": "Miscellaneous"
        },
        {
          "topic": "United Kingdom",
          "chapter": "Countries of the World"
        }
      ]
    }
  ],
  "is_new": true,
  "year": 2001
}