{
  "mcq": [
    {
      "statement": "To which religious group is Vatican City considered sacred?",
      "options": {
        "a": "Muslims",
        "b": "Hindus",
        "c": "Christians",
        "d": "Jews"
      },
      "one_liner": "Vatican City holds special religious significance for **Christians**.",
      "correct_option": "c",
      "suggestions": [
        {
          "topic": "Geographical Tags Attached with Names of Different Countries and Cities",
          "chapter": "Geography, Boundaries & Places"
        },
        {
          "topic": "Worldwide Famous Historic Buildings",
          "chapter": "World Historic Landmarks & Buildings"
        },
        {
          "topic": "Capitals of Countries",
          "chapter": "Countries of the World"
        },
        {
          "topic": "Geographical Tags Attached with Names of Different Countries and Cities",
          "chapter": "Geography, Boundaries & Places"
        }
      ]
    }
  ],
  "is_new": true
}